{"basics":{"name":"Mélanie Gaillochet","label":"Computer vision researcher","image":"","email":"melanie.gaillochet.1@ens.etsmtl.ca","phone":"(438) 527-2157","url":"https://Minimel.github.io","summary":"","profiles":[{"network":"","username":"","url":""}]},"work":[{"name":"BrainInnov","position":"Research Intern","url":"","startDate":"2025-01","endDate":"2025-06","summary":"","highlights":["Implemented segmentation and localization algorithms for lung cancer detection."]},{"name":"ÉTS Montréal","position":"Research Intern","url":"","startDate":"2020-10","endDate":"2021-04","summary":"Supervised by Prof. Hervé Lombaert","highlights":["Developped an active learning method for segmentation based on data uncertainty to minimize manual annotation of medical images."]},{"name":"Konigle Pte. Ltd","position":"R&D Scientist","url":"","startDate":"2019-10","endDate":"2020-03","summary":"","highlights":["Leveraged machine translation algorithms to augment and standardize transaction data of small businesses.","Implemented a product recommendation system based on transaction history."]},{"name":"Konigle Pte. Ltd","position":"R&D Intern","url":"","startDate":"2019-04","endDate":"2019-09","summary":"","highlights":["Developed an automated framework for business analytics and sales forecasting to improve the decision-making process of small businesses."]}],"education":[{"institution":"ÉTS Montréal & MILA-Quebec AI Institute & Polytechnique Montréal","location":"Montréal, Canada","url":"https://www.etsmtl.ca/","area":"Software Engineering and IT","studyType":"PhD","startDate":"2021-05","endDate":"","score":""},{"institution":"ETH Zürich","location":"Zürich, Switzerland","url":"https://www.ethz.ch/en.html","area":"Data Science","studyType":"Master of Science","startDate":"2017-09","endDate":"2020-12","score":""},{"institution":"McGill University","location":"Montréal, Canada","url":"mcgill.ca","area":"Physics","studyType":"Bachelor of Science","startDate":"2013-09","endDate":"2017-02","score":""}],"volunteer":[{"organization":"","location":"","position":"","url":"","startDate":"","endDate":"","summary":"","highlights":[""]}],"awards":[{"title":"PhD Excellence Scholarship","date":"2023","awarder":"Québec Research Funds (FRQNT)","url":"","summary":"3-year excellence scholarship for foreign PhD students."},{"title":"Internal Graduate Excellence Scholarship","date":"2023","awarder":"ÉTS Montreal","url":"","summary":""},{"title":"First-year PhD Scholarship","date":"2022","awarder":"Québec Bio-Imaging Network (RBIQ)","url":"","summary":""}],"certificates":[{"name":"","date":"","issuer":"","url":"","icon":""}],"publications":[{"name":"","publisher":"","releaseDate":"","url":"","summary":""}],"skills":[{"name":"","level":"","icon":"fa-solid fa-hashtag","keywords":[]}],"languages":[{"language":"French","fluency":"Native speaker","icon":""},{"language":"English","fluency":"Native speaker","icon":""},{"language":"Tagalog","fluency":"Native speaker","icon":""},{"language":"Spanish","fluency":"Fluent","icon":""},{"language":"German","fluency":"Beginner level","icon":""},{"language":"Japanese","fluency":"Beginner level","icon":""}],"interests":[{"name":"","icon":"fa-solid fa-tag","keywords":[]}],"references":[{"name":"Professor Hervé Lombaert","icon":"fa-solid fa-laptop","reference":"PhD Supervisor"},{"name":"Professor Christian Desrosiers","icon":"fa-solid ffa-laptop","reference":"PhD Supervisor"},{"name":"Professor Ender Konukoglu","icon":"fa-solid fa-laptop","reference":"Master thesis supervisor"}],"projects":[{"name":"","summary":"","highlights":[""],"startDate":"","endDate":"","url":""}]}